README.txt
bootstrap.py
buildout.cfg
pil.cfg
setup.py
docs/HISTORY.txt
docs/LICENSE.GPL
docs/LICENSE.txt
resources/README.txt
resources/theme/earthlingtwo/index.html
resources/theme/earthlingtwo/license.txt
resources/theme/earthlingtwo/manifest.cfg
resources/theme/earthlingtwo/rules.xml
resources/theme/earthlingtwo/static/style.css
resources/theme/earthlingtwo/static/images/img01.jpg
resources/theme/earthlingtwo/static/images/img02.jpg
resources/theme/earthlingtwo/static/images/img03.jpg
resources/theme/earthlingtwo/static/images/img04.jpg
resources/theme/earthlingtwo/static/images/img05.jpg
resources/theme/earthlingtwo/static/images/img06.jpg
resources/theme/earthlingtwo/static/images/img07.jpg
resources/theme/earthlingtwo/static/images/img08.jpg
resources/theme/earthlingtwo/static/images/img09.jpg
resources/theme/earthlingtwo/static/images/img10.gif
resources/theme/earthlingtwo/static/images/img11.gif
resources/theme/earthlingtwo/static/images/img12.jpg
resources/theme/earthlingtwo/static/images/img15.jpg
src/plone/__init__.py
src/plone.app.cmsui.egg-info/PKG-INFO
src/plone.app.cmsui.egg-info/SOURCES.txt
src/plone.app.cmsui.egg-info/dependency_links.txt
src/plone.app.cmsui.egg-info/entry_points.txt
src/plone.app.cmsui.egg-info/namespace_packages.txt
src/plone.app.cmsui.egg-info/not-zip-safe
src/plone.app.cmsui.egg-info/requires.txt
src/plone.app.cmsui.egg-info/top_level.txt
src/plone/app/__init__.py
src/plone/app/cmsui/__init__.py
src/plone/app/cmsui/addmenu.py
src/plone/app/cmsui/configure.zcml
src/plone/app/cmsui/displayoptions.py
src/plone/app/cmsui/fileupload.py
src/plone/app/cmsui/historypanel.py
src/plone/app/cmsui/interfaces.py
src/plone/app/cmsui/lockinfo.py
src/plone/app/cmsui/menu.py
src/plone/app/cmsui/overlaycontainer.py
src/plone/app/cmsui/sharing.py
src/plone/app/cmsui/structure.py
src/plone/app/cmsui/testing.py
src/plone/app/cmsui/uploadcapable.py
src/plone/app/cmsui/workflowpanel.py
src/plone/app/cmsui/bbb/__init__.py
src/plone/app/cmsui/bbb/configure.zcml
src/plone/app/cmsui/bbb/menulink.pt
src/plone/app/cmsui/bbb/menulink.py
src/plone/app/cmsui/bbb/null.pt
src/plone/app/cmsui/bbb/nullviewlet.py
src/plone/app/cmsui/bbb/profiles/bbb/actions.xml
src/plone/app/cmsui/bbb/profiles/bbb/cssregistry.xml
src/plone/app/cmsui/bbb/profiles/bbb/jsregistry.xml
