Metadata-Version: 1.0
Name: plone.app.cmsui
Version: 1.0a2
Summary: CMS user interface for Plone
Home-page: http://pypi.python.org/pypi/plone.app.cmsui
Author: Plone developers
Author-email: UNKNOWN
License: GPL
Keywords: plone ui
Platform: UNKNOWN
Classifier: Framework :: Plone
Classifier: Programming Language :: Python
Classifier: Topic :: Software Development :: Libraries :: Python Modules
